ffsubsync/__init__.py
ffsubsync/_version.py
ffsubsync/aligners.py
ffsubsync/constants.py
ffsubsync/ffmpeg_utils.py
ffsubsync/ffsubsync.py
ffsubsync/ffsubsync_gui.py
ffsubsync/file_utils.py
ffsubsync/generic_subtitles.py
ffsubsync/golden_section_search.py
ffsubsync/sklearn_shim.py
ffsubsync/speech_transformers.py
ffsubsync/subtitle_parser.py
ffsubsync/subtitle_transformers.py
ffsubsync/version.py
ffsubsync-0.4.30.dist-info/LICENSE
ffsubsync-0.4.30.dist-info/METADATA
ffsubsync-0.4.30.dist-info/WHEEL
ffsubsync-0.4.30.dist-info/entry_points.txt
ffsubsync-0.4.30.dist-info/top_level.txt
ffsubsync-0.4.30.dist-info/RECORD
