Metadata-Version: 2.1
Name: ffsubsync
Version: 0.4.30
Summary: Language-agnostic synchronization of subtitles with video.
Home-page: https://github.com/smacke/ffsubsync
Author: Stephen Macke
Author-email: stephen.macke@gmail.com
License: MIT
Classifier: Development Status :: 3 - Alpha
Classifier: Intended Audience :: End Users/Desktop
Classifier: License :: OSI Approved :: MIT License
Classifier: Natural Language :: English
Classifier: Programming Language :: Python :: 3.6
Classifier: Programming Language :: Python :: 3.7
Classifier: Programming Language :: Python :: 3.8
Classifier: Programming Language :: Python :: 3.9
Classifier: Programming Language :: Python :: 3.10
Classifier: Programming Language :: Python :: 3.11
Classifier: Programming Language :: Python :: 3.12
Classifier: Programming Language :: Python :: 3.13
Classifier: Topic :: Multimedia :: Sound/Audio :: Analysis
Classifier: Topic :: Multimedia :: Sound/Audio :: Speech
License-File: LICENSE
Requires-Dist: auditok (==0.1.5)
Requires-Dist: charset-normalizer
Requires-Dist: ffmpeg-python
Requires-Dist: numpy (>=1.12.0)
Requires-Dist: rich
Requires-Dist: setuptools
Requires-Dist: srt (>=3.0.0)
Requires-Dist: tqdm
Requires-Dist: typing-extensions
Requires-Dist: webrtcvad ; platform_system != "Windows"
Requires-Dist: webrtcvad-wheels ; platform_system == "Windows"
Requires-Dist: faust-cchardet ; python_version < "3.13"
Requires-Dist: pysubs2 ; python_version < "3.7"
Requires-Dist: chardet ; python_version >= "3.7"
Requires-Dist: pysubs2 (>=1.2.0) ; python_version >= "3.7"
